simple_3dviz/__init__.py
simple_3dviz/scenes.py
simple_3dviz/utils.py
simple_3dviz/behaviours/__init__.py
simple_3dviz/behaviours/io.py
simple_3dviz/behaviours/keyboard.py
simple_3dviz/behaviours/misc.py
simple_3dviz/behaviours/mouse.py
simple_3dviz/behaviours/movements.py
simple_3dviz/behaviours/trajectory.py
simple_3dviz/io/__init__.py
simple_3dviz/io/_utils.py
simple_3dviz/io/mesh.py
simple_3dviz/io/voxels.py
simple_3dviz/renderables/__init__.py
simple_3dviz/renderables/base.py
simple_3dviz/renderables/lines.py
simple_3dviz/renderables/mesh.py
simple_3dviz/renderables/spherecloud.py
simple_3dviz/scripts/__init__.py
simple_3dviz/scripts/func_viewer.py
simple_3dviz/scripts/mesh_viewer.py
simple_3dviz/window/__init__.py
simple_3dviz/window/base.py
simple_3dviz/window/wx.py
simple_3dviz-0.2.1.dist-info/LICENSE
simple_3dviz-0.2.1.dist-info/METADATA
simple_3dviz-0.2.1.dist-info/WHEEL
simple_3dviz-0.2.1.dist-info/entry_points.txt
simple_3dviz-0.2.1.dist-info/top_level.txt
simple_3dviz-0.2.1.dist-info/RECORD
