Metadata-Version: 2.1
Name: simple-3dviz
Version: 0.2.1
Summary: simple-3dviz is a simple visualization library for 3D 
Home-page: http://simple-3dviz.com
Maintainer: Angelos Katharopoulos, Despoina Paschalidou
Maintainer-email: angelos.katharopoulos@idiap.ch
License: MIT
Keywords: graphics geometry 3D
Platform: UNKNOWN
Classifier: Intended Audience :: Science/Research
Classifier: Intended Audience :: Developers
Classifier: License :: OSI Approved :: MIT License
Classifier: Topic :: Scientific/Engineering
Classifier: Programming Language :: Python
Classifier: Programming Language :: Python :: 2
Classifier: Programming Language :: Python :: 2.7
Classifier: Programming Language :: Python :: 3
Requires-Dist: moderngl
Requires-Dist: numpy
Requires-Dist: pyrr
Requires-Dist: plyfile
Requires-Dist: Pillow
